scribe_logger
