Metadata-Version: 1.1
Name: scribe-logger
Version: 1.3
Summary: Scribe log writer and logging handler.
Home-page: https://github.com/adilansari/python-scribe-logger
Author: Adil Ansari
Author-email: me@adilansari.com
License: MIT
Keywords: scribe logging
Platform: UNKNOWN
Classifier: Development Status :: 4 - Beta
Classifier: Intended Audience :: Developers
Classifier: Natural Language :: English
Classifier: Programming Language :: Python :: 2.7
Classifier: Topic :: Software Development :: Libraries
Classifier: Topic :: System :: Logging
Classifier: License :: OSI Approved :: MIT License
